EFN/EFNASM.py
EFN/EFNC.py
EFN/EFNKERNEL.py
EFN/__init__.py
EFN/core.py
EFN/corefor3d.py
EFN/coreforai.py
EFN/coreforbrowser.py
EFN/coreforcrypto.py
EFN/corefordiscordpy.py
EFN/coreforhtml.py
EFN/coreforimg.py
EFN/coreforinspect.py
EFN/coreforinternet.py
EFN/coreforkivy.py
EFN/coreformoviepy.py
EFN/coreforparamiko.py
EFN/coreforphonenumbers.py
EFN/coreforqrcode.py
EFN/coreforspeak.py
EFN/coreforssl.py
EFN/corefortensorflow.py
EFN/corefortorchai.py
EFN/coreforurl.py
EFN/coreforurml.py
EFN/coreforweather.py
EFN/BrowserCreator/__init__.py
EFN/BrowserCreator/core.py
efn-4.2.dist-info/METADATA
efn-4.2.dist-info/WHEEL
efn-4.2.dist-info/top_level.txt
efn-4.2.dist-info/RECORD
