Metadata-Version: 2.1
Name: EFN
Version: 4.2
Summary: A programming language in a Python library.
Author: Andrisgalaxy
Requires-Python: >=3.8
Requires-Dist: cefpython3
Requires-Dist: requests
Requires-Dist: beautifulsoup4
Requires-Dist: Pillow
Requires-Dist: psutil
Requires-Dist: qrcode
Requires-Dist: tkhtmlview
Requires-Dist: pyttsx3
Requires-Dist: pywebview
Requires-Dist: ursina
Requires-Dist: pygame
Requires-Dist: discord.py
Requires-Dist: deep-translator
Requires-Dist: google
Requires-Dist: pandas
Requires-Dist: phonenumbers
Requires-Dist: fastapi
Requires-Dist: keyboard
Requires-Dist: kivy
Requires-Dist: pytz
Requires-Dist: pycryptodome
Requires-Dist: librosa
Requires-Dist: numpy
Requires-Dist: mpmath
Requires-Dist: matplotlib
Requires-Dist: markovify
Requires-Dist: tensorflow
Requires-Dist: torch
Requires-Dist: tensorflow-hub
Requires-Dist: huggingface
Requires-Dist: huggingface-hub
Requires-Dist: moviepy
Requires-Dist: paramiko
Requires-Dist: typing
Requires-Dist: google-genai ; python_version >= "3.9"
